solc_json_parser/__init__.py
solc_json_parser/abi.py
solc_json_parser/ast_shared.py
solc_json_parser/base_parser.py
solc_json_parser/cli.py
solc_json_parser/combined_json_parser.py
solc_json_parser/consts.py
solc_json_parser/fields.py
solc_json_parser/fix_imports.py
solc_json_parser/flatten.py
solc_json_parser/opcodes.py
solc_json_parser/parser.py
solc_json_parser/standard_json_parser.py
solc_json_parser/version_cfg.py
solc_json_parser-0.1.9.dist-info/METADATA
solc_json_parser-0.1.9.dist-info/WHEEL
solc_json_parser-0.1.9.dist-info/entry_points.txt
solc_json_parser-0.1.9.dist-info/top_level.txt
solc_json_parser-0.1.9.dist-info/RECORD
