Metadata-Version: 2.1
Name: solc-json-parser
Version: 0.1.9
Summary: AST parser from solc json file
Author: SBIP
License: MIT
Requires-Dist: addict (>=2.4.0)
Requires-Dist: py-solc-x (>=1.1.1)
Requires-Dist: semantic-version (>=2.9.0)
Requires-Dist: pycryptodome (>=3.16.0)
Requires-Dist: utils (>=1.0.1)
